{
"type": "FeatureCollection", 
"features": [
{"type": "Feature", "id": 0, "properties": {"index": "1","name": "Molakhia", "image_url": "https://upload.wikimedia.org/wikipedia/commons/thumb/9/94/Syrian_Mlokhia.jpg/1024px-Syrian_Mlokhia.jpg", "restaurant":"Hosh Al Yasmine", "restaurant_url":"https://www.facebook.com/pages/Hosh-Al-Yasmine/335161666578656", "by":"Sari", "tags": ["Middle-eastern","Arab","Greens"]}, "geometry": { "type": "Point","coordinates": [35.83312123402884, 34.44037918777348] } },
{"type": "Feature", "id": 1, "properties": {"index": "2","name": "Borek", "image_url": "https://foto.haberler.com/haber/2020/11/25/borek-tarifleri-en-lezzetli-borek-tarifleri-13758966_5753_o.jpg", "restaurant":"Çiçek Börek","restaurant_url":"https://www.google.com/search?q=%C3%87i%C3%A7ek%20B%C3%B6rek&hl=en&source=hp&ei=z0RmYJrkNYqP9PwP5MudoA8&iflsig=AINFCbYAAAAAYGZS38zWovGBwFMmDPLTYkMcHmwLd7m2&oq=%C3%87i%C3%A7ek+B%C3%B6rek&gs_lcp=Cgdnd3Mtd2l6EAMyAggAMgUIABDJAzIGCAAQFhAeMgYIABAWEB4yBggAEBYQHjIGCAAQFhAeMgYIABAWEB4yBggAEBYQHjIGCAAQFhAeMgYIABAWEB5QjglYjglg0gtoAHAAeACAAYgBiAGIAZIBAzAuMZgBAKABAqABAaoBB2d3cy13aXo&sclient=gws-wiz&ved=2ahUKEwjs5Ov8h97vAhWTX80KHS_xCfUQvS4wAHoECAUQNA&uact=5&tbs=lf:1,lf_ui:9&tbm=lcl&rflfq=1&num=10&rldimm=7664924047462690473&lqi=Cg7Dh2nDp2VrIELDtnJla0jops_jnqqAgAhaKAoOw6dpw6dlayBiw7ZyZWsQABABGAAYASIOw6dpw6dlayBiw7ZyZWuSAQZiYWtlcnk&phdesc=AFP9ylPmkYo&rlst=f#rlfi=hd:;si:7664924047462690473,l,Cg7Dh2nDp2VrIELDtnJla0jops_jnqqAgAhaKAoOw6dpw6dlayBiw7ZyZWsQABABGAAYASIOw6dpw6dlayBiw7ZyZWuSAQZiYWtlcnk,y,AFP9ylPmkYo;mv:[[38.6809016,39.2286917],[38.673593499999996,39.2074359]];tbs:lrf:!1m4!1u3!2m2!3m1!1e1!1m4!1u2!2m2!2m1!1e1!2m1!1e2!2m1!1e3!3sIAE,lf:1,lf_ui:9", "by":"Ezgi", "tags": ["Vegetarian","Vegan","Pastry","Turkish","Middle-eastern"]}, "geometry": { "type": "Point","coordinates": [32.860431426982316, 39.92312918678572] } },
{"type": "Feature", "id": 2, "properties": {"index": "3","name": "Baklawa", "image_url": "https://shatila.com/blog/wp-content/uploads/2017/03/0616.jpg", "restaurant":"a","restaurant_url":"", "by":"a", "tags": ["Middle-eastern","Dessert"]}, "geometry": { "type": "Point","coordinates": [35.54283728219194, 33.868670151210225] } },
{"type": "Feature", "id": 3, "properties": {"index": "4","name": "Baklawa", "image_url": "https://st2.myideasoft.com/idea/gx/27/myassets/products/487/fistikli-hisir-baklava-15-jpg.jpeg?revision=1612026168", "restaurant":"a","restaurant_url":"a", "by":"a", "tags": ["Middle-eastern","Dessert"]}, "geometry": { "type": "Point","coordinates": [37.9167467, 40.2227753] } }
]}

